LICENSE.txt
py_classic_error.py
setup.py
py_classic_error.egg-info/PKG-INFO
py_classic_error.egg-info/SOURCES.txt
py_classic_error.egg-info/dependency_links.txt
py_classic_error.egg-info/top_level.txt